eyedropper.py
eyedropper-0.0.2.dist-info/METADATA
eyedropper-0.0.2.dist-info/RECORD
eyedropper-0.0.2.dist-info/WHEEL
eyedropper-0.0.2.dist-info/entry_points.txt
eyedropper-0.0.2.dist-info/top_level.txt
