Metadata-Version: 2.1
Name: eyedropper
Version: 0.0.2
Summary: Easily get color codes on your computer.
Home-page: https://github.com/umluizlima/eyedropper
Author: Luiz Lima
Author-email: umluizlima@gmail.com
License: MIT License
Platform: UNKNOWN
Classifier: Programming Language :: Python :: 3
Classifier: License :: OSI Approved :: MIT License
Classifier: Operating System :: OS Independent
Requires-Dist: pyautogui
Requires-Dist: pyperclip
